aud/__init__.py
bge/__init__.py
bge/app/__init__.py
bge/constraints/__init__.py
bge/events/__init__.py
bge/logic/__init__.py
bge/render/__init__.py
bge/texture/__init__.py
bge/types/__init__.py
bgl/__init__.py
blf/__init__.py
bmesh/__init__.py
bmesh/geometry.py
bmesh/ops.py
bmesh/types.py
bmesh/utils.py
bpy/__init__.py
bpy/context.py
bpy/path.py
bpy/props.py
bpy/types.py
bpy/app/__init__.py
bpy/app/handlers.py
bpy/app/translations.py
bpy/ops/__init__.py
bpy/ops/action.py
bpy/ops/anim.py
bpy/ops/armature.py
bpy/ops/boid.py
bpy/ops/brush.py
bpy/ops/buttons.py
bpy/ops/cachefile.py
bpy/ops/camera.py
bpy/ops/clip.py
bpy/ops/cloth.py
bpy/ops/console.py
bpy/ops/constraint.py
bpy/ops/curve.py
bpy/ops/cycles.py
bpy/ops/dpaint.py
bpy/ops/ed.py
bpy/ops/export_anim.py
bpy/ops/export_mesh.py
bpy/ops/export_scene.py
bpy/ops/file.py
bpy/ops/fluid.py
bpy/ops/font.py
bpy/ops/gpencil.py
bpy/ops/graph.py
bpy/ops/group.py
bpy/ops/image.py
bpy/ops/import_anim.py
bpy/ops/import_curve.py
bpy/ops/import_mesh.py
bpy/ops/import_scene.py
bpy/ops/info.py
bpy/ops/lamp.py
bpy/ops/lattice.py
bpy/ops/logic.py
bpy/ops/marker.py
bpy/ops/mask.py
bpy/ops/material.py
bpy/ops/mball.py
bpy/ops/mesh.py
bpy/ops/nla.py
bpy/ops/node.py
bpy/ops/object.py
bpy/ops/outliner.py
bpy/ops/paint.py
bpy/ops/paintcurve.py
bpy/ops/palette.py
bpy/ops/particle.py
bpy/ops/pose.py
bpy/ops/poselib.py
bpy/ops/ptcache.py
bpy/ops/render.py
bpy/ops/rigidbody.py
bpy/ops/safe_areas.py
bpy/ops/scene.py
bpy/ops/screen.py
bpy/ops/script.py
bpy/ops/sculpt.py
bpy/ops/sequencer.py
bpy/ops/sketch.py
bpy/ops/sound.py
bpy/ops/surface.py
bpy/ops/text.py
bpy/ops/texture.py
bpy/ops/time.py
bpy/ops/transform.py
bpy/ops/ui.py
bpy/ops/uv.py
bpy/ops/view2d.py
bpy/ops/view3d.py
bpy/ops/wm.py
bpy/ops/world.py
bpy/utils/__init__.py
bpy/utils/previews.py
bpy/utils/units.py
bpy_extras/__init__.py
bpy_extras/anim_utils.py
bpy_extras/image_utils.py
bpy_extras/io_utils.py
bpy_extras/keyconfig_utils.py
bpy_extras/mesh_utils.py
bpy_extras/object_utils.py
fake_blender_api_2.79-0.4.1.dist-info/LICENSE.txt
fake_blender_api_2.79-0.4.1.dist-info/METADATA
fake_blender_api_2.79-0.4.1.dist-info/WHEEL
fake_blender_api_2.79-0.4.1.dist-info/top_level.txt
fake_blender_api_2.79-0.4.1.dist-info/RECORD
