Metadata-Version: 2.1
Name: fake-blender-api-2.79
Version: 0.4.1
Summary: Fake Blender 2.79 Python API for code completion, including BGE
Home-page: https://github.com/bgempire/fake-blender-api-2.79
Download-URL: https://github.com/bgempire/fake-blender-api-2.79/archive/0.3.tar.gz
Author: Joel Gomes da Silva
Author-email: joelgomes1994@hotmail.com
License: GPLv3
Keywords: blender,bge,upbge,api,3d,bpy,mathutils,code,completion,autocomplete
Classifier: Development Status :: 3 - Alpha
Classifier: Intended Audience :: Developers
Classifier: Topic :: Multimedia :: Graphics :: 3D Modeling
Classifier: Topic :: Multimedia :: Graphics :: 3D Rendering
Classifier: Topic :: Text Editors :: Integrated Development Environments (IDE)
Classifier: License :: OSI Approved :: GNU General Public License v3 (GPLv3)
Classifier: Programming Language :: Python :: 3
License-File: LICENSE.txt
Requires-Dist: typing
